{
    "packageId"        : "4176830c-0477-4693-a06d-e0f4e77dd08a",
    "version"          : "1.0",
    "packageName"      : "ddwrt-router-driver",
    "author"           : "Neil Jackson",
    "minimumHEVersion" : "2.1.9",
    "dateReleased"     : "2021-02-21",
    "category": "Convenience",
    "description": "A driver for your dd-wrt router, to perform reboot.",
    "tags": [

    ],
    
    "drivers": [
        {
            "id"           : "1acf685a-4622-4183-b67b-2ff5c60f3f71",
            "version"      : "1.0",
            "namespace"    : "neiljackson1984",
            "name"         : "ddwrt-router",
            "required"     : true,
            "file"         : "ddwrt-router.driver.groovy",
            "deployInfo" : {
                "hubitatIdOfDriverOrApp"                   : "1031",
                "hubitatIdOfTestInstance"                  : "934",
                "testEndpoint"                             : "runTheTestCode",
                "urlOfHubitat"                             : "http://hubitat1.rattnow.com:3780",
                "nameOfEventToContainTestEndpointResponse" : "testEndpointResponse"
            }
        },        
        {
            "id"           : "ee402d20-d8ed-4c61-b155-313dfbde8fd4",
            "version"      : "1.0",
            "namespace"    : "neiljackson1984",
            "name"         : "ddwrt-child-virtual-button",
            "required"     : true,
            "file"         : "ddwrt-child-virtual-button.driver.groovy",
            "deployInfo" : {
                "hubitatIdOfDriverOrApp"                   : "1032",
                "urlOfHubitat"                             : "http://hubitat1.rattnow.com:3780"
            }
        }
    ]
    
}